pieceful/__init__.py
pieceful/enums.py
pieceful/exceptions.py
pieceful/facade.py
pieceful/parameter_parser.py
pieceful/parameters.py
pieceful/piece_data.py
pieceful/registry.py
pieceful/typing_utils.py
pieceful-1.0.0.dist-info/METADATA
pieceful-1.0.0.dist-info/WHEEL
pieceful-1.0.0.dist-info/RECORD
